pip_model/__init__.py
pip_model/pip_model.py
pip_model-0.6.dist-info/LICENSE
pip_model-0.6.dist-info/METADATA
pip_model-0.6.dist-info/WHEEL
pip_model-0.6.dist-info/top_level.txt
pip_model-0.6.dist-info/RECORD
