Metadata-Version: 2.1
Name: pip-model
Version: 0.6
Summary: string to date
Home-page: https://github.com/18832823200/pip_model
Author-email: zkw8119@163.com
License: MIT
Platform: any
License-File: LICENSE
